ATE/Algorithms.py
ATE/__init__.py
ATE/main_function.py
ATE/point_estimates.py
ATE/variance_estimates.py
ATE_python-0.0.2.dist-info/LICENSE
ATE_python-0.0.2.dist-info/METADATA
ATE_python-0.0.2.dist-info/WHEEL
ATE_python-0.0.2.dist-info/top_level.txt
ATE_python-0.0.2.dist-info/RECORD
