Metadata-Version: 2.1
Name: ATE-python
Version: 0.0.2
Summary: Nonparametric efficient inference of average treatment effects for observational data
Home-page: https://github.com/ross1456/ATE-python.git
Author: Ross
Author-email: rosscooper@link.cuhk.edu.hk
License: MIT
Classifier: Programming Language :: Python :: 3
Classifier: License :: OSI Approved :: MIT License
Classifier: Operating System :: OS Independent
Requires-Python: >=3.8
License-File: LICENSE
Requires-Dist: numpy
Requires-Dist: pandas
Requires-Dist: scipy
Requires-Dist: matplotlib
